{
  "words": [
    
    
    {
      "number": 422,
      "word": "degrade",
      "pos": "動詞",
      "meaning": "〜の質を下げる、降格させる、分解される",
      "nuance": "「段階（grade）を下へ（de）」持っていくイメージです。他動詞では「地位や質を傷つけ、低下させる」こと、自動詞では「（化学物質などが）自然に分解・劣化する」ことを表します。",
      "example_sections": [
        {
          "title": "例文（他動詞：〜の質・地位を下げる）",
          "examples": [
            {
              "en": "Pollution has degraded the quality of the lake water.",
              "ja": "汚染が湖水の質を低下させた。",
              "highlight": "degraded"
            },
            {
              "en": "Cruel punishments degrade both the punisher and the punished.",
              "ja": "残酷な罰は、罰する側と罰せられる側の両方の品位を落とす。",
              "highlight": "degrade"
            }
          ]
        },
        {
          "title": "例文（自動詞：劣化する・分解される）",
          "examples": [
            {
              "en": "Plastics can take hundreds of years to degrade in the ocean.",
              "ja": "プラスチックが海中で分解されるには何百年もかかる場合がある。",
              "highlight": "degrade"
            }
          ]
        }
      ],
      "etymology": "de (下に) + gradus (歩み・階段) <br>→ 階段を下りる",
      "synonyms": [
        {"word": "deteriorate", "trans": "悪化する"},
        {"word": "humiliate", "trans": "恥をかかせる"},
        {"word": "decompose", "trans": "分解する"}
      ],
      "antonyms": [
        {"word": "upgrade", "trans": "向上させる"},
        {"word": "improve", "trans": "改善する"},
        {"word": "enhance", "trans": "高める"}
      ],
      "related": [
        {"word": "degradation", "trans": "名詞：悪化・分解"},
        {"word": "biodegradable", "trans": "形容詞：生分解性の"}
      ]
    },
    {
      "number": "422-2",
      "word": "degradation",
      "pos": "名詞",
      "meaning": "悪化、低下、分解、(品位の)下落",
      "nuance": "質や価値、状態が徐々に損なわれていくプロセスを指します。環境分野では「環境破壊（environmental degradation）」、化学分野では「物質の分解」として頻出します。",
      "example_sections": [
        {
          "title": "例文",
          "examples": [
            {
              "en": "Environmental degradation is reaching a critical point in this region.",
              "ja": "この地域における環境悪化は危機的な状況に達している。",
              "highlight": "degradation"
            },
            {
              "en": "The degradation of traditional values concerns many older citizens.",
              "ja": "伝統的価値観の低下が、多くの高齢者の懸念となっている。",
              "highlight": "degradation"
            }
          ]
        }
      ],
      "etymology": "degrade (下げる) + ation (こと) <br>→ 段階を落とすこと",
      "synonyms": [
        {"word": "deterioration", "trans": "悪化"},
        {"word": "decline", "trans": "衰退・低下"},
        {"word": "breakdown", "trans": "崩壊・分解"}
      ],
      "antonyms": [
        {"word": "improvement", "trans": "改善"},
        {"word": "restoration", "trans": "修復・復元"},
        {"word": "enhancement", "trans": "向上"}
      ],
      "related": [
        {
          "word": "degrade",
          "trans": "動詞：下げる・分解する",
          "link": "422-degrade.html"
        }
      ]
    },
    {
      "number": 423,
      "word": "descent",
      "pos": "名詞",
      "meaning": "降下、下り坂、家系、血統",
      "nuance": "物理的に下へ移動すること、または祖先からの系統を表します。飛行機の降下や山の下りだけでなく、「of French descent（フランス系の）」のように血統の意味でも使われます。",
      "example_sections": [
        {
          "title": "例文（降下・下り）",
          "examples": [
            {
              "en": "The plane began its descent into Tokyo.",
              "ja": "飛行機は東京への降下を始めた。",
              "highlight": "descent"
            },
            {
              "en": "The descent down the mountain was more difficult than expected.",
              "ja": "山を下りるのは予想以上に困難だった。",
              "highlight": "descent"
            }
          ]
        },
        {
          "title": "例文（家系・血統）",
          "examples": [
            {
              "en": "She is of Japanese descent.",
              "ja": "彼女は日本系です。",
              "highlight": "descent"
            }
          ]
        }
      ],
      "etymology": "de (下に) + scent (登る) <br>→ 下に降りること",
      "synonyms": [
        {"word": "drop", "trans": "降下"},
        {"word": "decline", "trans": "下り坂"},
        {"word": "ancestry", "trans": "家系"}
      ],
      "antonyms": [
        {"word": "ascent", "trans": "上昇"},
        {"word": "climb", "trans": "登ること"}
      ],
      "related": [
        {"word": "descend", "trans": "動詞：降りる"},
        {"word": "descendant", "trans": "名詞：子孫"}
      ]
    },
    {
      "number": "423-2",
      "word": "descendant",
      "pos": "名詞",
      "meaning": "子孫、末裔",
      "nuance": "ある人物や集団から血統的に続く後の世代を指します。歴史的な人物の子孫や、生物学的な進化の系統でも使われます。",
      "example_sections": [
        {
          "title": "例文",
          "examples": [
            {
              "en": "He is a descendant of a famous samurai family.",
              "ja": "彼は有名な侍の家系の子孫です。",
              "highlight": "descendant"
            },
            {
              "en": "Many Americans are descendants of European immigrants.",
              "ja": "多くのアメリカ人はヨーロッパ移民の子孫です。",
              "highlight": "descendants"
            }
          ]
        }
      ],
      "etymology": "descend (降りる) + ant (人) <br>→ (血統を)降りてきた人",
      "synonyms": [
        {"word": "offspring", "trans": "子孫"},
        {"word": "heir", "trans": "相続人"},
        {"word": "progeny", "trans": "子孫"}
      ],
      "antonyms": [
        {"word": "ancestor", "trans": "祖先"},
        {"word": "forefather", "trans": "先祖"}
      ],
      "related": [
        {
          "word": "descent",
          "trans": "名詞：家系・血統",
          "link": "423-descent.html"
        },
        {
          "word": "descend",
          "trans": "動詞：降りる"
        }
      ]
    },
    {
      "number": "423-3",
      "word": "deforestation",
      "pos": "名詞",
      "meaning": "森林伐採、森林破壊",
      "nuance": "森林を大規模に伐採し、森がなくなることを指します。環境問題の文脈で頻出し、気候変動や生態系破壊との関連で議論されます。",
      "example_sections": [
        {
          "title": "例文",
          "examples": [
            {
              "en": "Deforestation in the Amazon is a major environmental concern.",
              "ja": "アマゾンでの森林伐採は主要な環境問題です。",
              "highlight": "Deforestation"
            },
            {
              "en": "The government is taking steps to prevent further deforestation.",
              "ja": "政府はさらなる森林破壊を防ぐための措置を講じている。",
              "highlight": "deforestation"
            }
          ]
        }
      ],
      "etymology": "de (除去) + forest (森) + ation (こと) <br>→ 森を取り除くこと",
      "synonyms": [
        {"word": "logging", "trans": "伐採"},
        {"word": "clearance", "trans": "開墾"},
        {"word": "tree-cutting", "trans": "木の伐採"}
      ],
      "antonyms": [
        {"word": "reforestation", "trans": "植林・再森林化"},
        {"word": "afforestation", "trans": "森林造成"}
      ],
      "related": [
        {"word": "forest", "trans": "名詞：森"},
        {"word": "deforest", "trans": "動詞：森林を伐採する"}
      ]
    },
    


    {
      "number": 441,
      "word": "color-blind",
      "pos": "形容詞",
      "meaning": "色覚異常の、色盲の、人種差別をしない",
      "nuance": "文字通りには色の区別がつかない状態を指しますが、比喩的には「人種や肌の色による差別をしない」という肯定的な意味でも使われます。",
      "example_sections": [
        {
          "title": "例文（医学的な意味）",
          "examples": [
            {
              "en": "He is color-blind and cannot distinguish red from green.",
              "ja": "彼は色覚異常で赤と緑の区別がつかない。",
              "highlight": "color-blind"
            }
          ]
        },
        {
          "title": "例文（比喩的な意味）",
          "examples": [
            {
              "en": "We should strive to be color-blind in our hiring practices.",
              "ja": "採用活動では人種差別をしないよう努めるべきだ。",
              "highlight": "color-blind"
            },
            {
              "en": "A truly color-blind society treats everyone equally.",
              "ja": "真に人種差別のない社会はすべての人を平等に扱う。",
              "highlight": "color-blind"
            }
          ]
        }
      ],
      "etymology": "color (色) + blind (見えない) <br>→ 色が見えない",
      "synonyms": [
        {"word": "colorblind", "trans": "色覚異常の（ハイフンなし）"},
        {"word": "race-neutral", "trans": "人種中立的な"}
      ],
      "antonyms": [
        {"word": "race-conscious", "trans": "人種を意識した"},
        {"word": "discriminatory", "trans": "差別的な"}
      ],
      "related": [
        {"word": "blind", "trans": "形容詞：盲目の"},
        {"word": "color blindness", "trans": "名詞：色覚異常"}
      ]
    },
    {
      "number": "441-2",
      "word": "blind",
      "pos": "形容詞/動詞",
      "meaning": "盲目の、見えない / 〜の目を見えなくする",
      "nuance": "視覚的に見えない状態だけでなく、「blind to ~（〜に気づかない）」のように比喩的にも使われます。動詞では一時的または永久的に視力を奪うことを表します。",
      "example_sections": [
        {
          "title": "例文（形容詞）",
          "examples": [
            {
              "en": "He has been blind since birth.",
              "ja": "彼は生まれつき目が見えない。",
              "highlight": "blind"
            },
            {
              "en": "She was blind to his faults.",
              "ja": "彼女は彼の欠点に気づいていなかった。",
              "highlight": "blind"
            }
          ]
        },
        {
          "title": "例文（動詞）",
          "examples": [
            {
              "en": "The bright light temporarily blinded me.",
              "ja": "強い光で一時的に目が見えなくなった。",
              "highlight": "blinded"
            }
          ]
        }
      ],
      "etymology": "古英語 blind (見えない) <br>→ ゲルマン祖語由来",
      "synonyms": [
        {"word": "sightless", "trans": "視力のない"},
        {"word": "unseeing", "trans": "見えない"},
        {"word": "oblivious", "trans": "気づかない（比喩）"}
      ],
      "antonyms": [
        {"word": "sighted", "trans": "目の見える"},
        {"word": "aware", "trans": "気づいている"}
      ],
      "related": [
        {
          "word": "color-blind",
          "trans": "形容詞：色覚異常の",
          "link": "441-color-blind.html"
        },
        {
          "word": "blindness",
          "trans": "名詞：盲目"
        }
      ]
    },
    {
      "number": 442,
      "word": "dazzle",
      "pos": "動詞/名詞",
      "meaning": "〜の目をくらませる、まばゆくする、魅了する",
      "nuance": "強い光で目がくらむことから、転じて「圧倒的な美しさや才能で人を魅了する」という意味でも使われます。ポジティブな驚きや感動を伴います。",
      "example_sections": [
        {
          "title": "例文（動詞：光で目をくらませる）",
          "examples": [
            {
              "en": "The sunlight reflecting off the snow dazzled my eyes.",
              "ja": "雪に反射する日光が私の目をくらませた。",
              "highlight": "dazzled"
            }
          ]
        },
        {
          "title": "例文（動詞：魅了する）",
          "examples": [
            {
              "en": "She dazzled the audience with her performance.",
              "ja": "彼女はその演技で観客を魅了した。",
              "highlight": "dazzled"
            },
            {
              "en": "The city's skyline dazzles visitors at night.",
              "ja": "その街のスカイラインは夜に訪問者を魅了する。",
              "highlight": "dazzles"
            }
          ]
        }
      ],
      "etymology": "中英語 daselen (目をくらます) <br>→ スカンジナビア語源",
      "synonyms": [
        {"word": "blind", "trans": "目をくらませる"},
        {"word": "bedazzle", "trans": "魅了する"},
        {"word": "impress", "trans": "感銘を与える"},
        {"word": "amaze", "trans": "驚かせる"}
      ],
      "antonyms": [
        {"word": "bore", "trans": "退屈させる"},
        {"word": "disappoint", "trans": "失望させる"}
      ],
      "related": [
        {"word": "dazzling", "trans": "形容詞：まばゆい、素晴らしい"},
        {"word": "dazzlement", "trans": "名詞：眩惑"}
      ]
    },
    {
      "number": 443,
      "word": "racial",
      "pos": "形容詞",
      "meaning": "人種の、人種に関する",
      "nuance": "人種に関連する事柄を表す中立的な形容詞です。「racial discrimination（人種差別）」「racial equality（人種平等）」など、社会問題の文脈で頻繁に使われます。",
      "example_sections": [
        {
          "title": "例文",
          "examples": [
            {
              "en": "Racial discrimination is prohibited by law in many countries.",
              "ja": "人種差別は多くの国で法律で禁止されている。",
              "highlight": "Racial"
            },
            {
              "en": "The organization works to promote racial harmony.",
              "ja": "その組織は人種間の調和を促進するために活動している。",
              "highlight": "racial"
            },
            {
              "en": "We must address racial inequality in our society.",
              "ja": "私たちは社会における人種的不平等に取り組まなければならない。",
              "highlight": "racial"
            }
          ]
        }
      ],
      "etymology": "race (人種) + ial (形容詞語尾) <br>→ 人種に関する",
      "synonyms": [
        {"word": "ethnic", "trans": "民族の"},
        {"word": "ethnological", "trans": "民族学的な"}
      ],
      "antonyms": [],
      "related": [
        {"word": "race", "trans": "名詞：人種"},
        {"word": "racism", "trans": "名詞：人種差別"},
        {"word": "racist", "trans": "名詞/形容詞：人種差別主義者/人種差別的な"}
      ]
    },
    {
      "number": "443-2",
      "word": "race",
      "pos": "名詞",
      "meaning": "人種、民族、競争、レース",
      "nuance": "「人種」という意味では生物学的・文化的集団を指し、「競争」という意味ではスピードを競うことを表します。文脈によって意味が大きく異なる多義語です。",
      "example_sections": [
        {
          "title": "例文（人種）",
          "examples": [
            {
              "en": "People of all races should be treated equally.",
              "ja": "すべての人種の人々は平等に扱われるべきだ。",
              "highlight": "races"
            },
            {
              "en": "The human race faces many challenges.",
              "ja": "人類は多くの課題に直面している。",
              "highlight": "race"
            }
          ]
        },
        {
          "title": "例文（競争・レース）",
          "examples": [
            {
              "en": "She won the race by a large margin.",
              "ja": "彼女は大差でそのレースに勝った。",
              "highlight": "race"
            }
          ]
        }
      ],
      "etymology": "イタリア語 razza (種類、血統) <br>→ 起源不詳",
      "synonyms": [
        {"word": "ethnicity", "trans": "民族性（人種の意味）"},
        {"word": "competition", "trans": "競争（レースの意味）"},
        {"word": "contest", "trans": "競技"}
      ],
      "antonyms": [],
      "related": [
        {
          "word": "racial",
          "trans": "形容詞：人種の",
          "link": "443-racial.html"
        },
        {
          "word": "racism",
          "trans": "名詞：人種差別"
        }
      ]
    },
    {
      "number": 444,
      "word": "tribal",
      "pos": "形容詞",
      "meaning": "部族の、種族の",
      "nuance": "部族社会や伝統的な集団に関することを表します。また比喩的に「集団への強い帰属意識」を意味する「tribalism（部族主義）」という概念でも使われます。",
      "example_sections": [
        {
          "title": "例文",
          "examples": [
            {
              "en": "Tribal customs have been passed down for generations.",
              "ja": "部族の習慣は何世代にもわたって受け継がれてきた。",
              "highlight": "Tribal"
            },
            {
              "en": "The region is home to many tribal communities.",
              "ja": "その地域には多くの部族社会が存在する。",
              "highlight": "tribal"
            },
            {
              "en": "Tribal conflicts have plagued the area for decades.",
              "ja": "部族間の紛争が何十年もこの地域を悩ませてきた。",
              "highlight": "Tribal"
            }
          ]
        }
      ],
      "etymology": "tribe (部族) + al (形容詞語尾) <br>→ 部族に関する",
      "synonyms": [
        {"word": "ethnic", "trans": "民族の"},
        {"word": "indigenous", "trans": "先住民の"},
        {"word": "native", "trans": "原住民の"}
      ],
      "antonyms": [
        {"word": "modern", "trans": "現代的な"},
        {"word": "cosmopolitan", "trans": "国際的な"}
      ],
      "related": [
        {"word": "tribe", "trans": "名詞：部族"},
        {"word": "tribalism", "trans": "名詞：部族主義"}
      ]
    },
    {
      "number": "444-2",
      "word": "tribe",
      "pos": "名詞",
      "meaning": "部族、種族、一族",
      "nuance": "伝統的な社会集団や血縁関係で結ばれた集団を指します。人類学的な文脈だけでなく、「a tribe of artists（芸術家の集団）」のように比喩的にも使われます。",
      "example_sections": [
        {
          "title": "例文",
          "examples": [
            {
              "en": "The tribe has lived in this area for thousands of years.",
              "ja": "その部族は何千年もこの地域に住んできた。",
              "highlight": "tribe"
            },
            {
              "en": "Each tribe has its own language and traditions.",
              "ja": "各部族には独自の言語と伝統がある。",
              "highlight": "tribe"
            },
            {
              "en": "The whole tribe gathered for the ceremony.",
              "ja": "部族全体が儀式のために集まった。",
              "highlight": "tribe"
            }
          ]
        }
      ],
      "etymology": "ラテン語 tribus (ローマの3部族) <br>→ 三分割された集団",
      "synonyms": [
        {"word": "clan", "trans": "氏族"},
        {"word": "group", "trans": "集団"},
        {"word": "community", "trans": "共同体"}
      ],
      "antonyms": [
        {"word": "individual", "trans": "個人"}
      ],
      "related": [
        {
          "word": "tribal",
          "trans": "形容詞：部族の",
          "link": "444-tribal.html"
        },
        {
          "word": "tribesman",
          "trans": "名詞：部族の一員"
        }
      ]
    },
    {
      "number": 445,
      "word": "impartial",
      "pos": "形容詞",
      "meaning": "公平な、偏らない、中立の",
      "nuance": "特定の側に偏ることなく、公正な判断や態度を保つことを表します。裁判官やジャーナリストなど、中立性が求められる立場で重要な概念です。",
      "example_sections": [
        {
          "title": "例文",
          "examples": [
            {
              "en": "Judges must remain impartial in all cases.",
              "ja": "裁判官はすべての事件において公平でなければならない。",
              "highlight": "impartial"
            },
            {
              "en": "The committee conducted an impartial investigation.",
              "ja": "委員会は公平な調査を実施した。",
              "highlight": "impartial"
            },
            {
              "en": "It's difficult to be completely impartial about one's own work.",
              "ja": "自分自身の仕事について完全に公平でいるのは難しい。",
              "highlight": "impartial"
            }
          ]
        }
      ],
      "etymology": "im (否定) + partial (偏った) <br>→ 偏っていない",
      "synonyms": [
        {"word": "unbiased", "trans": "偏見のない"},
        {"word": "neutral", "trans": "中立の"},
        {"word": "fair", "trans": "公平な"},
        {"word": "objective", "trans": "客観的な"}
      ],
      "antonyms": [
        {"word": "partial", "trans": "偏った"},
        {"word": "biased", "trans": "偏見のある"},
        {"word": "prejudiced", "trans": "先入観のある"}
      ],
      "related": [
        {"word": "impartiality", "trans": "名詞：公平性"},
        {"word": "partial", "trans": "形容詞：偏った"}
      ]
    },
    {
      "number": "445-2",
      "word": "partial",
      "pos": "形容詞",
      "meaning": "部分的な、不完全な、偏った、えこひいきする",
      "nuance": "「一部の」という中立的な意味と、「特定の側に偏っている」という否定的な意味の両方があります。「be partial to ~（〜が好きだ）」という表現もよく使われます。",
      "example_sections": [
        {
          "title": "例文（部分的な）",
          "examples": [
            {
              "en": "The project is only in partial completion.",
              "ja": "プロジェクトはまだ部分的にしか完成していない。",
              "highlight": "partial"
            },
            {
              "en": "There was a partial eclipse of the sun.",
              "ja": "部分日食があった。",
              "highlight": "partial"
            }
          ]
        },
        {
          "title": "例文（偏った・好む）",
          "examples": [
            {
              "en": "The referee was accused of being partial to the home team.",
              "ja": "審判はホームチームをえこひいきしていると非難された。",
              "highlight": "partial"
            },
            {
              "en": "I'm quite partial to chocolate cake.",
              "ja": "私はチョコレートケーキがとても好きです。",
              "highlight": "partial"
            }
          ]
        }
      ],
      "etymology": "ラテン語 partialis (部分の) <br>→ pars (部分) から派生",
      "synonyms": [
        {"word": "incomplete", "trans": "不完全な"},
        {"word": "biased", "trans": "偏った"},
        {"word": "fond of", "trans": "〜が好きな"}
      ],
      "antonyms": [
        {"word": "complete", "trans": "完全な"},
        {"word": "impartial", "trans": "公平な"},
        {"word": "total", "trans": "全体の"}
      ],
      "related": [
        {
          "word": "impartial",
          "trans": "形容詞：公平な",
          "link": "445-impartial.html"
        },
        {
          "word": "partially",
          "trans": "副詞：部分的に"
        }
      ]
    },
    {
      "number": 446,
      "word": "reasoning",
      "pos": "名詞",
      "meaning": "推論、論理的思考、理由づけ",
      "nuance": "論理的に考えて結論を導き出すプロセス、または何かを正当化する理由を表します。学術的な文脈や議論で頻繁に使われます。",
      "example_sections": [
        {
          "title": "例文",
          "examples": [
            {
              "en": "Your reasoning is flawed in several places.",
              "ja": "あなたの推論にはいくつかの箇所に欠陥がある。",
              "highlight": "reasoning"
            },
            {
              "en": "The court explained its reasoning in the decision.",
              "ja": "裁判所はその判決における理由づけを説明した。",
              "highlight": "reasoning"
            },
            {
              "en": "Good reasoning skills are essential for problem-solving.",
              "ja": "優れた論理的思考力は問題解決に不可欠だ。",
              "highlight": "reasoning"
            }
          ]
        }
      ],
      "etymology": "reason (理性、理由) + ing (名詞語尾) <br>→ 理性を使うこと",
      "synonyms": [
        {"word": "logic", "trans": "論理"},
        {"word": "rationale", "trans": "理論的根拠"},
        {"word": "argument", "trans": "論証"}
      ],
      "antonyms": [
        {"word": "irrationality", "trans": "非合理性"},
        {"word": "intuition", "trans": "直感"}
      ],
      "related": [
        {"word": "reason", "trans": "名詞/動詞：理由/推論する"},
        {"word": "reasonable", "trans": "形容詞：合理的な"}
      ]
    },
    {
      "number": "446-2",
      "word": "reasonable",
      "pos": "形容詞",
      "meaning": "合理的な、理にかなった、妥当な、適度な",
      "nuance": "理性や常識に基づいた判断や行動を表します。価格や量が「手頃な」「適度な」という意味でも使われ、日常会話で非常に頻繁に使われる単語です。",
      "example_sections": [
        {
          "title": "例文（合理的な）",
          "examples": [
            {
              "en": "That seems like a reasonable solution to the problem.",
              "ja": "それは問題に対する合理的な解決策のようだ。",
              "highlight": "reasonable"
            },
            {
              "en": "Any reasonable person would agree with this decision.",
              "ja": "理性的な人なら誰でもこの決定に同意するだろう。",
              "highlight": "reasonable"
            }
          ]
        },
        {
          "title": "例文（妥当な・適度な）",
          "examples": [
            {
              "en": "The hotel offers rooms at reasonable prices.",
              "ja": "そのホテルは手頃な価格で部屋を提供している。",
              "highlight": "reasonable"
            },
            {
              "en": "We completed the work in a reasonable amount of time.",
              "ja": "私たちは妥当な時間内に仕事を完了した。",
              "highlight": "reasonable"
            }
          ]
        }
      ],
      "etymology": "reason (理性) + able (できる) <br>→ 理性が働く",
      "synonyms": [
        {"word": "rational", "trans": "合理的な"},
        {"word": "sensible", "trans": "分別のある"},
        {"word": "fair", "trans": "公正な"},
        {"word": "moderate", "trans": "適度な"}
      ],
      "antonyms": [
        {"word": "unreasonable", "trans": "不合理な"},
        {"word": "irrational", "trans": "非合理的な"},
        {"word": "excessive", "trans": "過度の"}
      ],
      "related": [
        {
          "word": "reasoning",
          "trans": "名詞：推論",
          "link": "446-reasoning.html"
        },
        {
          "word": "reasonably",
          "trans": "副詞：合理的に"
        }
      ]
    },
    {
      "number": "446-3",
      "word": "reasonably",
      "pos": "副詞",
      "meaning": "合理的に、かなり、まあまあ、適度に",
      "nuance": "理性的な方法で、または「それなりに」「まずまず」という程度を表します。「reasonably well（まあまあうまく）」のように程度を和らげる表現でよく使われます。",
      "example_sections": [
        {
          "title": "例文",
          "examples": [
            {
              "en": "She handled the situation reasonably well.",
              "ja": "彼女はその状況をかなりうまく処理した。",
              "highlight": "reasonably"
            },
            {
              "en": "We can reasonably assume that he will attend.",
              "ja": "彼が出席すると合理的に推測できる。",
              "highlight": "reasonably"
            },
            {
              "en": "The test was reasonably difficult.",
              "ja": "試験は適度に難しかった。",
              "highlight": "reasonably"
            }
          ]
        }
      ],
      "etymology": "reasonable (合理的な) + ly (副詞語尾) <br>→ 合理的に",
      "synonyms": [
        {"word": "fairly", "trans": "かなり"},
        {"word": "moderately", "trans": "適度に"},
        {"word": "rationally", "trans": "合理的に"}
      ],
      "antonyms": [
        {"word": "unreasonably", "trans": "不合理に"},
        {"word": "extremely", "trans": "極端に"}
      ],
      "related": [
        {
          "word": "reasonable",
          "trans": "形容詞：合理的な",
          "link": "446-reasoning.html"
        }
      ]
    },
    {
      "number": "446-4",
      "word": "rational",
      "pos": "形容詞",
      "meaning": "理性的な、合理的な、筋の通った",
      "nuance": "感情ではなく論理や理性に基づいた判断や行動を表します。reasonableよりも論理性や知性が強調されます。",
      "example_sections": [
        {
          "title": "例文",
          "examples": [
            {
              "en": "Let's try to approach this in a rational manner.",
              "ja": "これに理性的な方法で取り組もう。",
              "highlight": "rational"
            },
            {
              "en": "His fears were not rational.",
              "ja": "彼の恐怖は理性的なものではなかった。",
              "highlight": "rational"
            },
            {
              "en": "A rational person would consider all the evidence.",
              "ja": "理性的な人ならすべての証拠を考慮するだろう。",
              "highlight": "rational"
            }
          ]
        }
      ],
      "etymology": "ラテン語 rationalis (理性の) <br>→ ratio (理性、計算) から派生",
      "synonyms": [
        {"word": "reasonable", "trans": "合理的な"},
        {"word": "logical", "trans": "論理的な"},
        {"word": "sensible", "trans": "分別のある"}
      ],
      "antonyms": [
        {"word": "irrational", "trans": "非合理的な"},
        {"word": "illogical", "trans": "非論理的な"},
        {"word": "emotional", "trans": "感情的な"}
      ],
      "related": [
        {"word": "rationality", "trans": "名詞：合理性"},
        {"word": "rationally", "trans": "副詞：合理的に"},
        {"word": "rationalize", "trans": "動詞：合理化する"}
      ]
    },
    {
      "number": "446-5",
      "word": "rationally",
      "pos": "副詞",
      "meaning": "理性的に、合理的に、論理的に",
      "nuance": "感情に流されず、論理的な思考に基づいて行動する様子を表します。科学的・学問的な文脈でよく使われます。",
      "example_sections": [
        {
          "title": "例文",
          "examples": [
            {
              "en": "We need to think about this rationally, not emotionally.",
              "ja": "これについては感情的にではなく理性的に考える必要がある。",
              "highlight": "rationally"
            },
            {
              "en": "She explained her position rationally and clearly.",
              "ja": "彼女は自分の立場を理性的かつ明確に説明した。",
              "highlight": "rationally"
            },
            {
              "en": "It's hard to behave rationally in a crisis.",
              "ja": "危機的状況で理性的に行動するのは難しい。",
              "highlight": "rationally"
            }
          ]
        }
      ],
      "etymology": "rational (理性的な) + ly (副詞語尾) <br>→ 理性的に",
      "synonyms": [
        {"word": "logically", "trans": "論理的に"},
        {"word": "reasonably", "trans": "合理的に"},
        {"word": "sensibly", "trans": "分別をもって"}
      ],
      "antonyms": [
        {"word": "irrationally", "trans": "非合理的に"},
        {"word": "emotionally", "trans": "感情的に"}
      ],
      "related": [
        {
          "word": "rational",
          "trans": "形容詞：理性的な",
          "link": "446-reasoning.html"
        },
        {
          "word": "rationality",
          "trans": "名詞：合理性"
        }
      ]
    },
    {
      "number": 447,
      "word": "irrational",
      "pos": "形容詞",
      "meaning": "非合理的な、不合理な、理性的でない",
      "nuance": "論理や理性に基づかない、感情的または不条理な判断や行動を表します。rationalの対義語として、否定的なニュアンスを持ちます。",
      "example_sections": [
        {
          "title": "例文",
          "examples": [
            {
              "en": "She has an irrational fear of flying.",
              "ja": "彼女は飛行機に対する不合理な恐怖を持っている。",
              "highlight": "irrational"
            },
            {
              "en": "It would be irrational to refuse such a generous offer.",
              "ja": "そのような寛大な申し出を断るのは非合理的だろう。",
              "highlight": "irrational"
            },
            {
              "en": "His irrational behavior alarmed his colleagues.",
              "ja": "彼の不合理な行動は同僚たちを心配させた。",
              "highlight": "irrational"
            }
          ]
        }
      ],
      "etymology": "ir (否定) + rational (理性的な) <br>→ 理性的でない",
      "synonyms": [
        {"word": "unreasonable", "trans": "不合理な"},
        {"word": "illogical", "trans": "非論理的な"},
        {"word": "absurd", "trans": "不条理な"}
      ],
      "antonyms": [
        {"word": "rational", "trans": "理性的な"},
        {"word": "logical", "trans": "論理的な"},
        {"word": "reasonable", "trans": "合理的な"}
      ],
      "related": [
        {"word": "irrationally", "trans": "副詞：非合理的に"},
        {"word": "irrationality", "trans": "名詞：非合理性"}
      ]
    },
    {
      "number": "447-2",
      "word": "illogically",
      "pos": "副詞",
      "meaning": "非論理的に、不合理に",
      "nuance": "論理的な筋道が通っていない方法で、または矛盾した形で行動・思考する様子を表します。",
      "example_sections": [
        {
          "title": "例文",
          "examples": [
            {
              "en": "He argued illogically and failed to convince anyone.",
              "ja": "彼は非論理的に議論し、誰も説得できなかった。",
              "highlight": "illogically"
            },
            {
              "en": "The policy was illogically designed and created confusion.",
              "ja": "その政策は非論理的に設計されており、混乱を生んだ。",
              "highlight": "illogically"
            }
          ]
        }
      ],
      "etymology": "illogical (非論理的な) + ly (副詞語尾) <br>→ 非論理的に",
      "synonyms": [
        {"word": "irrationally", "trans": "非合理的に"},
        {"word": "unreasonably", "trans": "不合理に"},
        {"word": "absurdly", "trans": "不条理に"}
      ],
      "antonyms": [
        {"word": "logically", "trans": "論理的に"},
        {"word": "rationally", "trans": "合理的に"},
        {"word": "sensibly", "trans": "分別をもって"}
      ],
      "related": [
        {
          "word": "irrational",
          "trans": "形容詞：非合理的な",
          "link": "447-irrational.html"
        },
        {
          "word": "illogical",
          "trans": "形容詞：非論理的な"
        }
      ]
    },
    {
      "number": 448,
      "word": "defect",
      "pos": "名詞/動詞",
      "meaning": "欠陥、欠点、不具合 / 亡命する、離脱する",
      "nuance": "名詞では製品や性質の「欠陥」、動詞では国や組織からの「離反・亡命」を意味します。動詞の場合は政治的な文脈で使われることが多いです。",
      "example_sections": [
        {
          "title": "例文（名詞：欠陥）",
          "examples": [
            {
              "en": "The car was recalled due to a safety defect.",
              "ja": "その車は安全上の欠陥のためにリコールされた。",
              "highlight": "defect"
            },
            {
              "en": "The software has several minor defects.",
              "ja": "そのソフトウェアにはいくつかの軽微な不具合がある。",
              "highlight": "defects"
            }
          ]
        },
        {
          "title": "例文（動詞：亡命する）",
          "examples": [
            {
              "en": "The spy defected to the West during the Cold War.",
              "ja": "そのスパイは冷戦中に西側に亡命した。",
              "highlight": "defected"
            }
          ]
        }
      ],
      "etymology": "ラテン語 defectus (欠けている) <br>→ de (離れて) + facere (する)",
      "synonyms": [
        {"word": "flaw", "trans": "欠陥"},
        {"word": "fault", "trans": "欠点"},
        {"word": "imperfection", "trans": "不完全さ"},
        {"word": "desert", "trans": "見捨てる（動詞）"}
      ],
      "antonyms": [
        {"word": "perfection", "trans": "完璧"},
        {"word": "advantage", "trans": "利点"}
      ],
      "related": [
        {"word": "defective", "trans": "形容詞：欠陥のある"},
        {"word": "defection", "trans": "名詞：離反・亡命"}
      ]
    },
    {
      "number": "448-2",
      "word": "defective",
      "pos": "形容詞",
      "meaning": "欠陥のある、不完全な、故障した",
      "nuance": "製品や機能に問題があり、正常に動作しない状態を表します。品質管理や製造業の文脈で頻繁に使われます。",
      "example_sections": [
        {
          "title": "例文",
          "examples": [
            {
              "en": "Please return any defective products within 30 days.",
              "ja": "欠陥のある製品は30日以内に返品してください。",
              "highlight": "defective"
            },
            {
              "en": "The machine was shut down due to a defective part.",
              "ja": "その機械は欠陥のある部品のため停止された。",
              "highlight": "defective"
            },
            {
              "en": "Defective merchandise will be replaced free of charge.",
              "ja": "不良品は無料で交換されます。",
              "highlight": "Defective"
            }
          ]
        }
      ],
      "etymology": "defect (欠陥) + ive (形容詞語尾) <br>→ 欠陥がある",
      "synonyms": [
        {"word": "faulty", "trans": "欠陥のある"},
        {"word": "flawed", "trans": "欠点のある"},
        {"word": "imperfect", "trans": "不完全な"},
        {"word": "broken", "trans": "壊れた"}
      ],
      "antonyms": [
        {"word": "perfect", "trans": "完璧な"},
        {"word": "flawless", "trans": "欠点のない"},
        {"word": "functional", "trans": "機能する"}
      ],
      "related": [
        {
          "word": "defect",
          "trans": "名詞：欠陥",
          "link": "448-defect.html"
        }
      ]
    },
    {
      "number": "448-3",
      "word": "defection",
      "pos": "名詞",
      "meaning": "離反、亡命、脱党、背信",
      "nuance": "国家、組織、党派などから離れて敵対する側に移ることを指します。政治的・軍事的な文脈で使われることが多く、裏切りのニュアンスを伴います。",
      "example_sections": [
        {
          "title": "例文",
          "examples": [
            {
              "en": "His defection to the opposing party shocked everyone.",
              "ja": "彼の野党への離反は皆を驚かせた。",
              "highlight": "defection"
            },
            {
              "en": "The defection of key members weakened the organization.",
              "ja": "主要メンバーの離反が組織を弱体化させた。",
              "highlight": "defection"
            },
            {
              "en": "The government tried to prevent further defections.",
              "ja": "政府はさらなる離反を防ごうとした。",
              "highlight": "defections"
            }
          ]
        }
      ],
      "etymology": "defect (離反する) + ion (名詞語尾) <br>→ 離反すること",
      "synonyms": [
        {"word": "desertion", "trans": "脱走・離反"},
        {"word": "betrayal", "trans": "裏切り"},
        {"word": "apostasy", "trans": "背教"}
      ],
      "antonyms": [
        {"word": "loyalty", "trans": "忠誠"},
        {"word": "allegiance", "trans": "忠誠"}
      ],
      "related": [
        {
          "word": "defect",
          "trans": "動詞：亡命する",
          "link": "448-defect.html"
        },
        {
          "word": "defector",
          "trans": "名詞：亡命者・離反者"
        }
      ]
    },
    {
      "number": 449,
      "word": "flaw",
      "pos": "名詞/動詞",
      "meaning": "欠陥、欠点、傷 / 〜に傷をつける",
      "nuance": "完璧さを損なう小さな欠点や傷を指します。defectよりも軽微なニュアンスで、性格や計画、物理的なものなど幅広く使われます。",
      "example_sections": [
        {
          "title": "例文（名詞）",
          "examples": [
            {
              "en": "There's a flaw in your argument.",
              "ja": "あなたの議論には欠陥がある。",
              "highlight": "flaw"
            },
            {
              "en": "The diamond has a small flaw that reduces its value.",
              "ja": "そのダイヤモンドには価値を下げる小さな傷がある。",
              "highlight": "flaw"
            },
            {
              "en": "His only flaw is his tendency to be too cautious.",
              "ja": "彼の唯一の欠点は慎重すぎる傾向だ。",
              "highlight": "flaw"
            }
          ]
        }
      ],
      "etymology": "中英語 flawe (薄片、破片) <br>→ スカンジナビア語源",
      "synonyms": [
        {"word": "defect", "trans": "欠陥"},
        {"word": "imperfection", "trans": "不完全さ"},
        {"word": "fault", "trans": "欠点"},
        {"word": "weakness", "trans": "弱点"}
      ],
      "antonyms": [
        {"word": "perfection", "trans": "完璧"},
        {"word": "strength", "trans": "強み"},
        {"word": "virtue", "trans": "美点"}
      ],
      "related": [
        {"word": "flawed", "trans": "形容詞：欠陥のある"},
        {"word": "flawless", "trans": "形容詞：完璧な"}
      ]
    },
    {
      "number": 450,
      "word": "inferiority",
      "pos": "名詞",
      "meaning": "劣等、下位、劣っていること",
      "nuance": "他と比べて質や地位が劣っている状態を表します。心理学では「inferiority complex（劣等感）」という表現で頻繁に使われます。",
      "example_sections": [
        {
          "title": "例文",
          "examples": [
            {
              "en": "He struggled with feelings of inferiority throughout his childhood.",
              "ja": "彼は子供時代を通じて劣等感に苦しんだ。",
              "highlight": "inferiority"
            },
            {
              "en": "The study revealed the inferiority of the old method.",
              "ja": "その研究は古い方法の劣位性を明らかにした。",
              "highlight": "inferiority"
            },
            {
              "en": "She has an inferiority complex about her appearance.",
              "ja": "彼女は自分の容姿に劣等感を持っている。",
              "highlight": "inferiority"
            }
          ]
        }
      ],
      "etymology": "inferior (劣った) + ity (名詞語尾) <br>→ 劣っていること",
      "synonyms": [
        {"word": "inadequacy", "trans": "不十分さ"},
        {"word": "deficiency", "trans": "欠乏"},
        {"word": "weakness", "trans": "弱さ"}
      ],
      "antonyms": [
        {"word": "superiority", "trans": "優越"},
        {"word": "excellence", "trans": "卓越"}
      ],
      "related": [
        {"word": "inferior", "trans": "形容詞：劣った"},
        {"word": "inferiority complex", "trans": "名詞句：劣等感"}
      ]
    },
    {
      "number": "450-2",
      "word": "inferior",
      "pos": "形容詞/名詞",
      "meaning": "劣った、下位の、粗悪な / 目下の人",
      "nuance": "質、地位、能力などが他より低いことを表します。比較の文脈で「inferior to ~（〜より劣る）」という形でよく使われます。",
      "example_sections": [
        {
          "title": "例文（形容詞）",
          "examples": [
            {
              "en": "This product is inferior to the competition.",
              "ja": "この製品は競合製品より劣っている。",
              "highlight": "inferior"
            },
            {
              "en": "The quality of the copy was inferior to the original.",
              "ja": "コピーの品質はオリジナルより劣っていた。",
              "highlight": "inferior"
            },
            {
              "en": "She refused to accept inferior work from her team.",
              "ja": "彼女はチームからの粗悪な仕事を受け入れることを拒否した。",
              "highlight": "inferior"
            }
          ]
        }
      ],
      "etymology": "ラテン語 inferior (より低い) <br>→ inferus (下の) の比較級",
      "synonyms": [
        {"word": "substandard", "trans": "基準以下の"},
        {"word": "poor", "trans": "劣った"},
        {"word": "second-rate", "trans": "二流の"}
      ],
      "antonyms": [
        {"word": "superior", "trans": "優れた"},
        {"word": "excellent", "trans": "優秀な"},
        {"word": "premium", "trans": "高級な"}
      ],
      "related": [
        {
          "word": "inferiority",
          "trans": "名詞：劣等",
          "link": "450-inferiority.html"
        }
      ]
    },
    {
      "number": 451,
      "word": "lesser",
      "pos": "形容詞",
      "meaning": "より小さい、より少ない、より劣った",
      "nuance": "「less」の比較級形で、重要性や程度がより低いことを表します。「the lesser of two evils（二つの悪のうちより小さい方）」のような慣用表現でよく使われます。",
      "example_sections": [
        {
          "title": "例文",
          "examples": [
            {
              "en": "This is a problem of lesser importance.",
              "ja": "これはそれほど重要でない問題だ。",
              "highlight": "lesser"
            },
            {
              "en": "He chose the lesser of two evils.",
              "ja": "彼は二つの悪のうちましな方を選んだ。",
              "highlight": "lesser"
            },
            {
              "en": "Lesser-known artists often struggle to get recognition.",
              "ja": "あまり知られていない芸術家は認知を得るのに苦労することが多い。",
              "highlight": "Lesser-known"
            }
          ]
        }
      ],
      "etymology": "less (より少ない) + er (比較級語尾) <br>→ より少ない",
      "synonyms": [
        {"word": "minor", "trans": "より小さい"},
        {"word": "inferior", "trans": "劣った"},
        {"word": "smaller", "trans": "より小さい"}
      ],
      "antonyms": [
        {"word": "greater", "trans": "より大きい"},
        {"word": "superior", "trans": "優れた"},
        {"word": "major", "trans": "主要な"}
      ],
      "related": [
        {"word": "less", "trans": "形容詞/副詞：より少ない"},
        {"word": "least", "trans": "形容詞/副詞：最も少ない"}
      ]
    },
    {
      "number": 452,
      "word": "superiority",
      "pos": "名詞",
      "meaning": "優越、優位、優秀さ",
      "nuance": "他より優れている状態や、上位にあることを表します。「superiority complex（優越感）」という心理学用語でも使われます。",
      "example_sections": [
        {
          "title": "例文",
          "examples": [
            {
              "en": "The team demonstrated their superiority on the field.",
              "ja": "チームはフィールドで彼らの優位性を示した。",
              "highlight": "superiority"
            },
            {
              "en": "She has a superiority complex and looks down on others.",
              "ja": "彼女は優越感を持っており、他人を見下している。",
              "highlight": "superiority"
            },
            {
              "en": "The superiority of this technology is clear.",
              "ja": "この技術の優秀さは明らかだ。",
              "highlight": "superiority"
            }
          ]
        }
      ],
      "etymology": "superior (優れた) + ity (名詞語尾) <br>→ 優れていること",
      "synonyms": [
        {"word": "dominance", "trans": "優勢"},
        {"word": "excellence", "trans": "卓越"},
        {"word": "supremacy", "trans": "至上"}
      ],
      "antonyms": [
        {"word": "inferiority", "trans": "劣等"},
        {"word": "weakness", "trans": "弱さ"}
      ],
      "related": [
        {"word": "superior", "trans": "形容詞：優れた"},
        {"word": "superiority complex", "trans": "名詞句：優越感"}
      ]
    },
    {
      "number": "452-2",
      "word": "superior",
      "pos": "形容詞/名詞",
      "meaning": "優れた、上位の、高品質の / 上司、上官",
      "nuance": "質、地位、能力などが他より高いことを表します。「superior to ~（〜より優れている）」という形で比較を表現します。名詞としては職場での上司を指します。",
      "example_sections": [
        {
          "title": "例文（形容詞）",
          "examples": [
            {
              "en": "This model is superior to all previous versions.",
              "ja": "このモデルは以前のすべてのバージョンより優れている。",
              "highlight": "superior"
            },
            {
              "en": "The restaurant offers superior quality at reasonable prices.",
              "ja": "そのレストランは手頃な価格で高品質を提供している。",
              "highlight": "superior"
            }
          ]
        },
        {
          "title": "例文（名詞：上司）",
          "examples": [
            {
              "en": "You should report this matter to your superior.",
              "ja": "この件は上司に報告すべきです。",
              "highlight": "superior"
            }
          ]
        }
      ],
      "etymology": "ラテン語 superior (より高い) <br>→ superus (上の) の比較級",
      "synonyms": [
        {"word": "better", "trans": "より良い"},
        {"word": "excellent", "trans": "優秀な"},
        {"word": "premium", "trans": "高級な"},
        {"word": "boss", "trans": "上司（名詞）"}
      ],
      "antonyms": [
        {"word": "inferior", "trans": "劣った"},
        {"word": "subordinate", "trans": "下位の"},
        {"word": "poor", "trans": "劣った"}
      ],
      "related": [
        {
          "word": "superiority",
          "trans": "名詞：優越",
          "link": "452-superiority.html"
        }
      ]
    },
    {
      "number": 453,
      "word": "ethical",
      "pos": "形容詞",
      "meaning": "倫理的な、道徳的な、正しい",
      "nuance": "道徳や倫理に適合した行動や判断を表します。ビジネスや医療の分野で「ethical behavior（倫理的行動）」「ethical issues（倫理的問題）」といった形で頻繁に使われます。",
      "example_sections": [
        {
          "title": "例文",
          "examples": [
            {
              "en": "The company is committed to ethical business practices.",
              "ja": "その会社は倫理的なビジネス慣行に取り組んでいる。",
              "highlight": "ethical"
            },
            {
              "en": "Is it ethical to use animals in scientific experiments?",
              "ja": "科学実験で動物を使うことは倫理的だろうか？",
              "highlight": "ethical"
            },
            {
              "en": "Doctors must make ethical decisions every day.",
              "ja": "医師は毎日倫理的な決定を下さなければならない。",
              "highlight": "ethical"
            }
          ]
        }
      ],
      "etymology": "ethic (倫理) + al (形容詞語尾) <br>→ 倫理に関する",
      "synonyms": [
        {"word": "moral", "trans": "道徳的な"},
        {"word": "right", "trans": "正しい"},
        {"word": "principled", "trans": "原則に基づいた"}
      ],
      "antonyms": [
        {"word": "unethical", "trans": "非倫理的な"},
        {"word": "immoral", "trans": "不道徳な"},
        {"word": "wrong", "trans": "間違った"}
      ],
      "related": [
        {"word": "ethic", "trans": "名詞：倫理"},
        {"word": "ethics", "trans": "名詞：倫理学"},
        {"word": "ethically", "trans": "副詞：倫理的に"}
      ]
    },
    {
      "number": "453-2",
      "word": "ethic",
      "pos": "名詞",
      "meaning": "倫理、道徳観、行動規範",
      "nuance": "個人や集団の行動の指針となる道徳的原則を指します。「work ethic（労働倫理）」のように特定の分野での価値観を表現する際によく使われます。",
      "example_sections": [
        {
          "title": "例文",
          "examples": [
            {
              "en": "She has a strong work ethic and never misses a deadline.",
              "ja": "彼女は強い労働倫理を持っており、締め切りに遅れることはない。",
              "highlight": "ethic"
            },
            {
              "en": "The Protestant ethic emphasizes hard work and discipline.",
              "ja": "プロテスタント倫理は勤勉と規律を重視する。",
              "highlight": "ethic"
            },
            {
              "en": "His personal ethic guides all his decisions.",
              "ja": "彼の個人的な倫理観がすべての決定を導いている。",
              "highlight": "ethic"
            }
          ]
        }
      ],
      "etymology": "ギリシャ語 ethikos (道徳の) <br>→ ethos (性格、習慣) から派生",
      "synonyms": [
        {"word": "morality", "trans": "道徳"},
        {"word": "principle", "trans": "原則"},
        {"word": "value", "trans": "価値観"}
      ],
      "antonyms": [],
      "related": [
        {
          "word": "ethical",
          "trans": "形容詞：倫理的な",
          "link": "453-ethical.html"
        },
        {
          "word": "ethics",
          "trans": "名詞：倫理学"
        }
      ]
    },
    {
      "number": "453-3",
      "word": "ethics",
      "pos": "名詞",
      "meaning": "倫理学、道徳、倫理規範",
      "nuance": "道徳的原則の体系や、倫理学という学問分野を指します。単数扱いで「倫理学」、複数扱いで「倫理規範」の意味になります。",
      "example_sections": [
        {
          "title": "例文（倫理学）",
          "examples": [
            {
              "en": "She is studying medical ethics at university.",
              "ja": "彼女は大学で医療倫理学を学んでいる。",
              "highlight": "ethics"
            },
            {
              "en": "Ethics is a branch of philosophy.",
              "ja": "倫理学は哲学の一分野である。",
              "highlight": "Ethics"
            }
          ]
        },
        {
          "title": "例文（倫理規範）",
          "examples": [
            {
              "en": "The company's ethics are clearly stated in the handbook.",
              "ja": "会社の倫理規範はハンドブックに明確に記載されている。",
              "highlight": "ethics"
            },
            {
              "en": "Professional ethics require confidentiality.",
              "ja": "職業倫理は守秘義務を求める。",
              "highlight": "ethics"
            }
          ]
        }
      ],
      "etymology": "ethic (倫理) の複数形 <br>→ ギリシャ語 ethikos から",
      "synonyms": [
        {"word": "morals", "trans": "道徳"},
        {"word": "principles", "trans": "原則"},
        {"word": "moral philosophy", "trans": "道徳哲学"}
      ],
      "antonyms": [],
      "related": [
        {
          "word": "ethical",
          "trans": "形容詞：倫理的な",
          "link": "453-ethical.html"
        },
        {
          "word": "ethic",
          "trans": "名詞：倫理"
        }
      ]
    },
    {
      "number": 454,
      "word": "virtuous",
      "pos": "形容詞",
      "meaning": "高潔な、徳の高い、善良な",
      "nuance": "道徳的に優れた性質や行動を表します。単に「良い」だけでなく、高い道徳的基準を持つというニュアンスがあり、やや格式ばった表現です。",
      "example_sections": [
        {
          "title": "例文",
          "examples": [
            {
              "en": "She led a virtuous life dedicated to helping others.",
              "ja": "彼女は他者を助けることに捧げられた高潔な人生を送った。",
              "highlight": "virtuous"
            },
            {
              "en": "His virtuous behavior earned him respect in the community.",
              "ja": "彼の善良な行動は地域社会で尊敬を得た。",
              "highlight": "virtuous"
            },
            {
              "en": "The story celebrates virtuous characters who overcome evil.",
              "ja": "その物語は悪を克服する高潔な登場人物を称賛している。",
              "highlight": "virtuous"
            }
          ]
        }
      ],
      "etymology": "virtue (美徳) + ous (形容詞語尾) <br>→ 美徳を持つ",
      "synonyms": [
        {"word": "moral", "trans": "道徳的な"},
        {"word": "righteous", "trans": "正義の"},
        {"word": "upright", "trans": "正直な"},
        {"word": "noble", "trans": "高潔な"}
      ],
      "antonyms": [
        {"word": "immoral", "trans": "不道徳な"},
        {"word": "wicked", "trans": "邪悪な"},
        {"word": "corrupt", "trans": "腐敗した"}
      ],
      "related": [
        {"word": "virtue", "trans": "名詞：美徳"},
        {"word": "virtuously", "trans": "副詞：高潔に"}
      ]
    },
    {
      "number": "454-2",
      "word": "conscientious",
      "pos": "形容詞",
      "meaning": "良心的な、誠実な、勤勉な",
      "nuance": "責任感を持って丁寧に仕事や義務を果たす様子を表します。細部まで注意を払い、手を抜かない人を褒める際によく使われます。",
      "example_sections": [
        {
          "title": "例文",
          "examples": [
            {
              "en": "She is a conscientious worker who pays attention to every detail.",
              "ja": "彼女はすべての細部に注意を払う良心的な労働者だ。",
              "highlight": "conscientious"
            },
            {
              "en": "The company seeks conscientious employees who take pride in their work.",
              "ja": "会社は自分の仕事に誇りを持つ誠実な従業員を求めている。",
              "highlight": "conscientious"
            },
            {
              "en": "He made a conscientious effort to improve his skills.",
              "ja": "彼はスキルを向上させるために良心的な努力をした。",
              "highlight": "conscientious"
            }
          ]
        }
      ],
      "etymology": "ラテン語 conscientiosus (良心的な) <br>→ conscientia (良心) から派生",
      "synonyms": [
        {"word": "diligent", "trans": "勤勉な"},
        {"word": "meticulous", "trans": "細心の"},
        {"word": "thorough", "trans": "徹底的な"},
        {"word": "responsible", "trans": "責任感のある"}
      ],
      "antonyms": [
        {"word": "careless", "trans": "不注意な"},
        {"word": "negligent", "trans": "怠慢な"},
        {"word": "irresponsible", "trans": "無責任な"}
      ],
      "related": [
        {
          "word": "virtuous",
          "trans": "形容詞：高潔な",
          "link": "454-virtuous.html"
        },
        {
          "word": "conscience", "trans": "名詞：良心"},
        {"word": "conscientiously", "trans": "副詞：良心的に"}
      ]
    },
    {
      "number": "454-3",
      "word": "righteous",
      "pos": "形容詞",
      "meaning": "正義の、正しい、道徳的に正しい",
      "nuance": "道徳的・宗教的に正しいとされる行動や態度を表します。「righteous indignation（義憤）」のように正当な怒りを表現する際にも使われます。時に独善的なニュアンスも持ちます。",
      "example_sections": [
        {
          "title": "例文",
          "examples": [
            {
              "en": "They fought for a righteous cause.",
              "ja": "彼らは正義の大義のために戦った。",
              "highlight": "righteous"
            },
            {
              "en": "His righteous anger at the injustice was understandable.",
              "ja": "その不正に対する彼の義憤は理解できるものだった。",
              "highlight": "righteous"
            },
            {
              "en": "She lived according to righteous principles.",
              "ja": "彼女は正しい原則に従って生きた。",
              "highlight": "righteous"
            }
          ]
        }
      ],
      "etymology": "古英語 rihtwis (正しい + 賢い) <br>→ right (正しい) + wise (賢い)",
      "synonyms": [
        {"word": "virtuous", "trans": "高潔な"},
        {"word": "moral", "trans": "道徳的な"},
        {"word": "just", "trans": "公正な"},
        {"word": "upright", "trans": "正直な"}
      ],
      "antonyms": [
        {"word": "wicked", "trans": "邪悪な"},
        {"word": "sinful", "trans": "罪深い"},
        {"word": "immoral", "trans": "不道徳な"}
      ],
      "related": [
        {
          "word": "virtuous",
          "trans": "形容詞：高潔な",
          "link": "454-virtuous.html"
        },
        {
          "word": "righteousness", "trans": "名詞：正義"},
        {"word": "righteously", "trans": "副詞：正義に"}
      ]
    },
    {
      "number": 455,
      "word": "blindness",
      "pos": "名詞",
      "meaning": "盲目、失明、無知、無視",
      "nuance": "視覚的に見えない状態だけでなく、比喩的に「事実や真実に気づかないこと」「意図的に無視すること」も表します。",
      "example_sections": [
        {
          "title": "例文（視覚的な盲目）",
          "examples": [
            {
              "en": "The disease can cause permanent blindness if left untreated.",
              "ja": "その病気は治療しないと永久的な失明を引き起こす可能性がある。",
              "highlight": "blindness"
            },
            {
              "en": "Color blindness affects millions of people worldwide.",
              "ja": "色覚異常は世界中で何百万人もの人々に影響を与えている。",
              "highlight": "blindness"
            }
          ]
        },
        {
          "title": "例文（比喩的な盲目）",
          "examples": [
            {
              "en": "His blindness to her suffering was shocking.",
              "ja": "彼女の苦しみに対する彼の無視は衝撃的だった。",
              "highlight": "blindness"
            },
            {
              "en": "Moral blindness prevented them from seeing the truth.",
              "ja": "道徳的な盲目が彼らが真実を見ることを妨げた。",
              "highlight": "blindness"
            }
          ]
        }
      ],
      "etymology": "blind (盲目の) + ness (名詞語尾) <br>→ 盲目の状態",
      "synonyms": [
        {"word": "sightlessness", "trans": "視力喪失"},
        {"word": "ignorance", "trans": "無知（比喩）"},
        {"word": "unawareness", "trans": "気づかないこと"}
      ],
      "antonyms": [
        {"word": "sight", "trans": "視力"},
        {"word": "vision", "trans": "視覚"},
        {"word": "awareness", "trans": "気づき"}
      ],
      "related": [
        {"word": "blind", "trans": "形容詞：盲目の"},
        {"word": "color-blind", "trans": "形容詞：色覚異常の"}
      ]
    },
    {
      "number": 456,
      "word": "dominant",
      "pos": "形容詞",
      "meaning": "支配的な、優勢な、主要な",
      "nuance": "他より強い影響力を持ち、主導的な立場にあることを表します。生物学では「優性の」、音楽では「属音の」という専門的な意味もあります。",
      "example_sections": [
        {
          "title": "例文",
          "examples": [
            {
              "en": "English is the dominant language in international business.",
              "ja": "英語は国際ビジネスにおいて支配的な言語である。",
              "highlight": "dominant"
            },
            {
              "en": "The company holds a dominant position in the market.",
              "ja": "その会社は市場で優勢な地位を占めている。",
              "highlight": "dominant"
            },
            {
              "en": "He has a dominant personality that influences others.",
              "ja": "彼は他者に影響を与える支配的な性格を持っている。",
              "highlight": "dominant"
            }
          ]
        }
      ],
      "etymology": "ラテン語 dominans (支配する) <br>→ dominari (支配する) の現在分詞",
      "synonyms": [
        {"word": "predominant", "trans": "主要な"},
        {"word": "prevailing", "trans": "優勢な"},
        {"word": "ruling", "trans": "支配的な"},
        {"word": "leading", "trans": "主導的な"}
      ],
      "antonyms": [
        {"word": "subordinate", "trans": "従属的な"},
        {"word": "minor", "trans": "小さな"},
        {"word": "weak", "trans": "弱い"}
      ],
      "related": [
        {"word": "dominance", "trans": "名詞：支配"},
        {"word": "dominate", "trans": "動詞：支配する"},
        {"word": "domination", "trans": "名詞：支配"}
      ]
    },
    {
      "number": "456-2",
      "word": "dominance",
      "pos": "名詞",
      "meaning": "支配、優勢、優位",
      "nuance": "他より強い力や影響力を持っている状態を表します。政治、ビジネス、自然界など幅広い文脈で使われます。",
      "example_sections": [
        {
          "title": "例文",
          "examples": [
            {
              "en": "The team established their dominance early in the game.",
              "ja": "チームは試合の早い段階で優位性を確立した。",
              "highlight": "dominance"
            },
            {
              "en": "The country's economic dominance has declined in recent years.",
              "ja": "その国の経済的優位は近年低下している。",
              "highlight": "dominance"
            },
            {
              "en": "Male dominance in the workplace is gradually changing.",
              "ja": "職場における男性支配は徐々に変化している。",
              "highlight": "dominance"
            }
          ]
        }
      ],
      "etymology": "dominant (支配的な) + ance (名詞語尾) <br>→ 支配すること",
      "synonyms": [
        {"word": "supremacy", "trans": "至上"},
        {"word": "control", "trans": "支配"},
        {"word": "superiority", "trans": "優越"},
        {"word": "power", "trans": "権力"}
      ],
      "antonyms": [
        {"word": "subordination", "trans": "従属"},
        {"word": "weakness", "trans": "弱さ"},
        {"word": "inferiority", "trans": "劣等"}
      ],
      "related": [
        {
          "word": "dominant",
          "trans": "形容詞：支配的な",
          "link": "456-dominant.html"
        },
        {
          "word": "dominate",
          "trans": "動詞：支配する"
        }
      ]
    },
    {
      "number": "456-3",
      "word": "dominate",
      "pos": "動詞",
      "meaning": "〜を支配する、優位に立つ、圧倒する",
      "nuance": "力や影響力によって他を制御したり、圧倒的に優勢な立場にあることを表します。物理的にも比喩的にも使われます。",
      "example_sections": [
        {
          "title": "例文",
          "examples": [
            {
              "en": "One company dominates the smartphone market.",
              "ja": "一つの会社がスマートフォン市場を支配している。",
              "highlight": "dominates"
            },
            {
              "en": "The castle dominates the surrounding landscape.",
              "ja": "その城は周囲の景観を圧倒している。",
              "highlight": "dominates"
            },
            {
              "en": "He tends to dominate conversations.",
              "ja": "彼は会話を支配する傾向がある。",
              "highlight": "dominate"
            }
          ]
        }
      ],
      "etymology": "ラテン語 dominari (支配する) <br>→ dominus (主人) から派生",
      "synonyms": [
        {"word": "control", "trans": "支配する"},
        {"word": "rule", "trans": "統治する"},
        {"word": "govern", "trans": "支配する"},
        {"word": "overwhelm", "trans": "圧倒する"}
      ],
      "antonyms": [
        {"word": "submit", "trans": "服従する"},
        {"word": "yield", "trans": "譲る"}
      ],
      "related": [
        {
          "word": "dominant",
          "trans": "形容詞：支配的な",
          "link": "456-dominant.html"
        },
        {
          "word": "domination",
          "trans": "名詞：支配"
        }
      ]
    },
    {
      "number": "456-4",
      "word": "domination",
      "pos": "名詞",
      "meaning": "支配、制圧、統治",
      "nuance": "完全な支配や制御を意味し、dominanceよりも強制的で抑圧的なニュアンスがあります。政治的・軍事的な文脈でよく使われます。",
      "example_sections": [
        {
          "title": "例文",
          "examples": [
            {
              "en": "The country fought against foreign domination.",
              "ja": "その国は外国の支配に対して戦った。",
              "highlight": "domination"
            },
            {
              "en": "The empire's domination lasted for centuries.",
              "ja": "その帝国の支配は何世紀も続いた。",
              "highlight": "domination"
            },
            {
              "en": "They resisted the domination of the ruling class.",
              "ja": "彼らは支配階級の支配に抵抗した。",
              "highlight": "domination"
            }
          ]
        }
      ],
      "etymology": "dominate (支配する) + ion (名詞語尾) <br>→ 支配すること",
      "synonyms": [
        {"word": "control", "trans": "支配"},
        {"word": "rule", "trans": "統治"},
        {"word": "oppression", "trans": "抑圧"},
        {"word": "subjugation", "trans": "征服"}
      ],
      "antonyms": [
        {"word": "liberation", "trans": "解放"},
        {"word": "freedom", "trans": "自由"},
        {"word": "independence", "trans": "独立"}
      ],
      "related": [
        {
          "word": "dominate",
          "trans": "動詞：支配する",
          "link": "456-dominant.html"
        },
        {
          "word": "dominant",
          "trans": "形容詞：支配的な"
        }
      ]
    },
    {
      "number": "456-5",
      "word": "prevalent",
      "pos": "形容詞",
      "meaning": "普及している、流行している、広く見られる",
      "nuance": "ある時期や場所で広く存在し、一般的であることを表します。病気、意見、習慣などが広まっている状態を表現する際に使われます。",
      "example_sections": [
        {
          "title": "例文",
          "examples": [
            {
              "en": "Obesity is becoming increasingly prevalent in developed countries.",
              "ja": "肥満は先進国でますます広まっている。",
              "highlight": "prevalent"
            },
            {
              "en": "This belief was prevalent in the 19th century.",
              "ja": "この信念は19世紀に広く見られた。",
              "highlight": "prevalent"
            },
            {
              "en": "Smartphone use is prevalent among all age groups.",
              "ja": "スマートフォンの使用はすべての年齢層で普及している。",
              "highlight": "prevalent"
            }
          ]
        }
      ],
      "etymology": "ラテン語 praevalens (優勢な) <br>→ praevalere (優勢である) から",
      "synonyms": [
        {"word": "widespread", "trans": "広まった"},
        {"word": "common", "trans": "一般的な"},
        {"word": "prevailing", "trans": "優勢な"},
        {"word": "dominant", "trans": "支配的な"}
      ],
      "antonyms": [
        {"word": "rare", "trans": "まれな"},
        {"word": "uncommon", "trans": "珍しい"},
        {"word": "scarce", "trans": "乏しい"}
      ],
      "related": [
        {"word": "prevalence", "trans": "名詞：普及"},
        {"word": "prevail", "trans": "動詞：優勢である"}
      ]
    },
    {
      "number": "456-6",
      "word": "prevailing",
      "pos": "形容詞",
      "meaning": "優勢な、一般的な、支配的な",
      "nuance": "ある時期に最も一般的で影響力がある状態を表します。「prevailing wind（卓越風）」のように特定の方向に吹く風を指す気象用語としても使われます。",
      "example_sections": [
        {
          "title": "例文",
          "examples": [
            {
              "en": "The prevailing opinion is that the policy will succeed.",
              "ja": "一般的な意見はその政策が成功するというものだ。",
              "highlight": "prevailing"
            },
            {
              "en": "Prevailing economic conditions favor growth.",
              "ja": "優勢な経済状況は成長を有利にしている。",
              "highlight": "Prevailing"
            },
            {
              "en": "The prevailing winds come from the west.",
              "ja": "卓越風は西から吹いてくる。",
              "highlight": "prevailing"
            }
          ]
        }
      ],
      "etymology": "prevail (優勢である) + ing (形容詞語尾) <br>→ 優勢である",
      "synonyms": [
        {"word": "dominant", "trans": "支配的な"},
        {"word": "prevalent", "trans": "普及している"},
        {"word": "current", "trans": "現在の"},
        {"word": "widespread", "trans": "広まった"}
      ],
      "antonyms": [
        {"word": "rare", "trans": "まれな"},
        {"word": "uncommon", "trans": "珍しい"},
        {"word": "minor", "trans": "小さな"}
      ],
      "related": [
        {"word": "prevail", "trans": "動詞：優勢である"},
        {"word": "prevalent", "trans": "形容詞：普及している"}
      ]
    },
    {
      "number": "456-7",
      "word": "prevail",
      "pos": "動詞",
      "meaning": "勝つ、優勢である、普及している、説得する",
      "nuance": "競争や困難に打ち勝つこと、または広く存在することを表します。「prevail over/against ~（〜に勝つ）」「prevail upon/on ~（〜を説得する）」という形でよく使われます。",
      "example_sections": [
        {
          "title": "例文（勝つ・優勢である）",
          "examples": [
            {
              "en": "Justice will prevail in the end.",
              "ja": "正義は最終的に勝つだろう。",
              "highlight": "prevail"
            },
            {
              "en": "Common sense prevailed over emotion.",
              "ja": "常識が感情に勝った。",
              "highlight": "prevailed"
            }
          ]
        },
        {
          "title": "例文（普及している）",
          "examples": [
            {
              "en": "Calm prevails after the storm.",
              "ja": "嵐の後に静けさが広がっている。",
              "highlight": "prevails"
            }
          ]
        },
        {
          "title": "例文（説得する）",
          "examples": [
            {
              "en": "She prevailed upon him to change his mind.",
              "ja": "彼女は彼を説得して考えを変えさせた。",
              "highlight": "prevailed upon"
            }
          ]
        }
      ],
      "etymology": "ラテン語 praevalere (優勢である) <br>→ prae (前に) + valere (強い)",
      "synonyms": [
        {"word": "triumph", "trans": "勝利する"},
        {"word": "win", "trans": "勝つ"},
        {"word": "dominate", "trans": "支配する"},
        {"word": "persuade", "trans": "説得する"}
      ],
      "antonyms": [
        {"word": "lose", "trans": "負ける"},
        {"word": "fail", "trans": "失敗する"},
        {"word": "surrender", "trans": "降伏する"}
      ],
      "related": [
        {"word": "prevailing", "trans": "形容詞：優勢な"},
        {"word": "prevalent", "trans": "形容詞：普及している"},
        {"word": "prevalence", "trans": "名詞：普及"}
      ]
    },
    {
    "number": 457,
    "word": "norm",
    "pos": "名詞",
    "meaning": "規範、基準、標準",
    "nuance": "社会的な「当たり前」や「期待される行動」を指すことが多い単語です。また、統計的な平均や標準的な状態を指すこともあります。",
    "example_sections": [
      {
        "title": "例文（社会的規範）",
        "examples": [
          {
            "en": "We must follow the social norms of the community.",
            "ja": "私たちはそのコミュニティの社会規範に従わなければならない。",
            "highlight": "norms"
          }
        ]
      },
      {
        "title": "例文（標準・平均）",
        "examples": [
          {
            "en": "Working from home has become the norm in many industries.",
            "ja": "在宅勤務は多くの業界で標準（当たり前）になっている。",
            "highlight": "norm"
          }
        ]
      }
    ],
    "etymology": "ラテン語 norma (大工の使う直角定規、尺度) <br>→ 物事の正しさを測る基準",
    "synonyms": [
      {"word": "standard", "trans": "標準"},
      {"word": "convention", "trans": "慣習"},
      {"word": "criterion", "trans": "基準"}
    ],
    "antonyms": [
      {"word": "exception", "trans": "例外"},
      {"word": "anomaly", "trans": "異例、変則"}
    ],
    "related": [
      {"word": "normal", "trans": "形容詞：標準的な、普通の"},
      {"word": "normalize", "trans": "動詞：正常化する、標準化する"},
      {"word": "normative", "trans": "形容詞：規範的な"}
    ]
  },
  {
    "number": 458,
    "word": "paradigm",
    "pos": "名詞",
    "meaning": "理論的枠組み、パラダイム、典型的な例",
    "nuance": "ある時代や分野において支配的な「考え方の枠組み」を指します。劇的な変化を「paradigm shift」と呼ぶのはビジネスや科学で非常に一般的です。",
    "example_sections": [
      {
        "title": "例文",
        "examples": [
          {
            "en": "The discovery of DNA led to a new paradigm in biology.",
            "ja": "DNAの発見は、生物学における新しいパラダイム（理論的枠組み）をもたらした。",
            "highlight": "paradigm"
          },
          {
            "en": "The company is a paradigm of modern management.",
            "ja": "その会社は現代経営の典型的な例である。",
            "highlight": "paradigm"
          }
        ]
      }
    ],
    "etymology": "ギリシャ語 paradeigma (パターン、手本) <br>→ para (横に) + deigma (示すもの) = 並べて見せる手本",
    "synonyms": [
      {"word": "framework", "trans": "枠組み"},
      {"word": "model", "trans": "模型、手本"},
      {"word": "pattern", "trans": "型"}
    ],
    "antonyms": [
      {"word": "chaos", "trans": "混沌"},
      {"word": "anomaly", "trans": "（既存の枠組みに合わない）例外"}
    ],
    "related": [
      {"word": "paradigm shift", "trans": "名詞：パラダイムシフト（発想の転換）"},
      {"word": "paradigmatic", "trans": "形容詞：典型的な"}
    ]
  },
  {
    "number": 459,
    "word": "thereby",
    "pos": "副詞",
    "meaning": "それによって、その結果として",
    "nuance": "文語的でフォーマルな表現です。前の文で述べた行動や手段によって、何かが達成されたり引き起こされたりすることを示します。",
    "example_sections": [
      {
        "title": "例文",
        "examples": [
          {
            "en": "He signed the contract, thereby agreeing to the terms.",
            "ja": "彼は契約書に署名し、それによって条件に同意した。",
            "highlight": "thereby"
          },
          {
            "en": "Diet and exercise reduce weight, thereby improving health.",
            "ja": "食事と運動は体重を減らし、その結果として健康を改善する。",
            "highlight": "thereby"
          }
        ]
      }
    ],
    "etymology": "there (そこ) + by (〜によって) <br>→ それによって",
    "synonyms": [
      {"word": "thus", "trans": "したがって"},
      {"word": "consequently", "trans": "その結果として"},
      {"word": "accordingly", "trans": "それに応じて"}
    ],
    "antonyms": [
      {"word": "nevertheless", "trans": "それにもかかわらず"},
      {"word": "regardless", "trans": "関係なく"}
    ],
    "related": [
      {"word": "thereafter", "trans": "副詞：その後"},
      {"word": "therein", "trans": "副詞：その中に"}
    ]
  },
  {
    "number": 460,
    "word": "invisible",
    "pos": "形容詞",
    "meaning": "目に見えない、不可視の",
    "nuance": "物理的に光を通すため見えない状態だけでなく、社会的に無視されている、あるいは存在が意識されない状態（invisible laborなど）にも使われます。",
    "example_sections": [
      {
        "title": "例文（物理的）",
        "examples": [
          {
            "en": "The gas is colorless and invisible to the naked eye.",
            "ja": "そのガスは無色で、肉眼では見えない。",
            "highlight": "invisible"
          }
        ]
      },
      {
        "title": "例文（比喩的）",
        "examples": [
          {
            "en": "He felt invisible at the large party.",
            "ja": "彼はその大きなパーティーで、自分の存在が無視されているように感じた。",
            "highlight": "invisible"
          }
        ]
      }
    ],
    "etymology": "in (否定) + visible (見える) <br>→ 見ることができない",
    "synonyms": [
      {"word": "unseen", "trans": "見られていない"},
      {"word": "hidden", "trans": "隠された"},
      {"word": "imperceptible", "trans": "知覚できない"}
    ],
    "antonyms": [
      {"word": "visible", "trans": "目に見える"},
      {"word": "apparent", "trans": "明らかな"}
    ],
    "related": [
      {"word": "invisibility", "trans": "名詞：目に見えないこと"},
      {"word": "visibly", "trans": "副詞：目に見えて"}
    ]
  },
  {
    "number": "460-2",
    "word": "visible",
    "pos": "形容詞",
    "meaning": "目に見える、明白な、人目に付く",
    "nuance": "視覚的に確認できることや、証拠や変化がはっきりと分かることを表します。公の場での露出度が高い場合（visible role）にも使われます。",
    "example_sections": [
      {
        "title": "例文（視覚的）",
        "examples": [
          {
            "en": "The stars are clearly visible on a cloudless night.",
            "ja": "雲のない夜には星がはっきりと見える。",
            "highlight": "visible"
          }
        ]
      },
      {
        "title": "例文（明白な）",
        "examples": [
          {
            "en": "There was a visible improvement in his health.",
            "ja": "彼の健康状態には明らかな改善が見られた。",
            "highlight": "visible"
          }
        ]
      }
    ],
    "etymology": "ラテン語 videre (見る) + ible (できる) <br>→ 見ることができる",
    "synonyms": [
      {"word": "observable", "trans": "観察できる"},
      {"word": "noticeable", "trans": "目立つ"},
      {"word": "evident", "trans": "明白な"}
    ],
    "antonyms": [
      {"word": "invisible", "trans": "目に見えない"},
      {"word": "obscure", "trans": "不明瞭な"}
    ],
    "related": [
      {"word": "visibility", "trans": "名詞：視界、露出度"},
      {"word": "vision", "trans": "名詞：視力、ビジョン"},
      {"word": "visual", "trans": "形容詞：視覚の"}
    ]
  },
  {
    "number": 461,
    "word": "fundamentally",
    "pos": "副詞",
    "meaning": "根本的に、本質的に",
    "nuance": "物事の最も基礎となる部分や、本質に触れる際に使われます。「根本から覆す」「本質的に異なる」といった強い強調を伴うことが多いです。",
    "example_sections": [
      {
        "title": "例文",
        "examples": [
          {
            "en": "The two systems are fundamentally different from each other.",
            "ja": "その2つのシステムは、互いに根本的に異なっている。",
            "highlight": "fundamentally"
          },
          {
            "en": "We need to fundamentally rethink our approach to the problem.",
            "ja": "私たちはその問題へのアプローチを根本的に再考する必要がある。",
            "highlight": "fundamentally"
          }
        ]
      }
    ],
    "etymology": "fundamental (基礎の) + ly (副詞語尾) <br>→ 基礎の部分から",
    "synonyms": [
      {"word": "essentially", "trans": "本質的に"},
      {"word": "basically", "trans": "基本的に"},
      {"word": "radically", "trans": "根本的に（過激に）"}
    ],
    "antonyms": [
      {"word": "superficially", "trans": "表面上は"},
      {"word": "slightly", "trans": "わずかに"}
    ],
    "related": [
      {"word": "fundamental", "trans": "形容詞：根本的な"},
      {"word": "foundation", "trans": "名詞：土台、基礎"},
      {"word": "fundamentalism", "trans": "名詞：原理主義"}
    ]
  },
  {
    "number": "461-2",
    "word": "fundamental",
    "pos": "形容詞",
    "meaning": "根本的な、基本的な、主要な",
    "nuance": "建物でいう「土台」のように、それがないと全体が成り立たないほど重要な要素を指します。名詞（fundamentals）で「基本、原理」を指すこともあります。",
    "example_sections": [
      {
        "title": "例文",
        "examples": [
          {
            "en": "Freedom of speech is a fundamental human right.",
            "ja": "言論の自由は、基本的人権である。",
            "highlight": "fundamental"
          },
          {
            "en": "There is a fundamental flaw in your argument.",
            "ja": "あなたの主張には根本的な欠陥がある。",
            "highlight": "fundamental"
          }
        ]
      }
    ],
    "etymology": "ラテン語 fundamentum (土台) <br>→ 底にある基盤となるもの",
    "synonyms": [
      {"word": "basic", "trans": "基礎的な"},
      {"word": "primary", "trans": "主要な"},
      {"word": "elementary", "trans": "初歩的な"}
    ],
    "antonyms": [
      {"word": "secondary", "trans": "二次的な、付随的な"},
      {"word": "incidental", "trans": "些細な"}
    ],
    "related": [
      {"word": "fundamentally", "trans": "副詞：根本的に"},
      {"word": "fundamentals", "trans": "名詞：基本、諸原則"}
    ]
  },
  {
    "number": 462,
    "word": "elemental",
    "pos": "形容詞",
    "meaning": "自然の力の、基本的な、元素の",
    "nuance": "「element（要素・元素）」から派生し、自然界の抗えない強大な力（嵐や火など）や、非常に単純かつ不可欠な性質を指します。fundamentalよりも「生々しい自然の力」や「構成要素」というニュアンスが強いです。",
    "example_sections": [
      {
        "title": "例文（自然の力）",
        "examples": [
          {
            "en": "They struggled against the elemental force of the storm.",
            "ja": "彼らは嵐という自然の猛威（抗えない力）に抗って苦闘した。",
            "highlight": "elemental"
          }
        ]
      },
      {
        "title": "例文（基本的な）",
        "examples": [
          {
            "en": "The story explores the elemental human emotions of love and fear.",
            "ja": "その物語は、愛や恐怖といった人間としての根源的な感情を掘り下げている。",
            "highlight": "elemental"
          }
        ]
      }
    ],
    "etymology": "element (要素、自然の力) + al (形容詞語尾) <br>→ 要素に関する",
    "synonyms": [
      {"word": "primitive", "trans": "原始的な"},
      {"word": "natural", "trans": "自然の"},
      {"word": "essential", "trans": "不可欠な"}
    ],
    "antonyms": [
      {"word": "complex", "trans": "複雑な"},
      {"word": "artificial", "trans": "人工的な"}
    ],
    "related": [
      {"word": "element", "trans": "名詞：要素、元素"},
      {"word": "elementary", "trans": "形容詞：初歩的な"}
    ]
  },
  {
    "number": 463,
    "word": "integral",
    "pos": "形容詞",
    "meaning": "不可欠な、組み込まれた、整数の",
    "nuance": "全体を構成する一部として「欠かせない」ことを強調します。ある機能が最初から内蔵されている状態（built-in）を指すことも多いです。数学では「積分の」という意味でも使われます。",
    "example_sections": [
      {
        "title": "例文（不可欠な）",
        "examples": [
          {
            "en": "Music is an integral part of his life.",
            "ja": "音楽は彼の人生にとって不可欠な（切り離せない）一部だ。",
            "highlight": "integral"
          }
        ]
      },
      {
        "title": "例文（組み込まれた）",
        "examples": [
          {
            "en": "The team needs a leader with integral skills in both management and tech.",
            "ja": "チームは、経営と技術の両面で統合されたスキルを持つリーダーを必要としている。",
            "highlight": "integral"
          }
        ]
      }
    ],
    "etymology": "ラテン語 integer (手つかずの、完全な) <br>→ 欠けていない全体を構成するもの",
    "synonyms": [
      {"word": "essential", "trans": "本質的な"},
      {"word": "indispensable", "trans": "なしでは済まされない"},
      {"word": "component", "trans": "構成要素の"}
    ],
    "antonyms": [
      {"word": "peripheral", "trans": "周囲の、重要でない"},
      {"word": "optional", "trans": "任意の、あってもなくてもよい"}
    ],
    "related": [
      {"word": "integrate", "trans": "動詞：統合する"},
      {"word": "integrity", "trans": "名詞：誠実さ、完全性"},
      {"word": "integration", "trans": "名詞：統合"}
    ]
  }

    
  ]
}
